{
  "_fv": 28,
  "_type": "recipe",
  "definition": {
    "recipeType": "Crafting",
    "xpReward": 0.0,
    "cookingTime": 200,
    "recipeRetstackSize": 3,
    "group": "",
    "recipeShapeless": false,
    "recipeSlots": [
      {
        "value": ""
      },
      {
        "value": ""
      },
      {
        "value": ""
      },
      {
        "value": "Blocks.BLACK_GLAZED_TERRACOTTA"
      },
      {
        "value": "Items.STICK"
      },
      {
        "value": "Blocks.BLACK_GLAZED_TERRACOTTA"
      },
      {
        "value": "Blocks.BLACK_GLAZED_TERRACOTTA"
      },
      {
        "value": "Items.STICK"
      },
      {
        "value": "Blocks.BLACK_GLAZED_TERRACOTTA"
      }
    ],
    "recipeReturnStack": {
      "value": "CUSTOM:BlackGlazedTerracottaFence"
    },
    "name": "black_glazed_terracotta_fence_recipe",
    "namespace": "mod"
  }
}